loghtml/__init__.py
loghtml/config.py
loghtml/core.py
loghtml/template.html
loghtml/writer.py
py_html_logger-0.1.16.dist-info/licenses/LICENSE
py_html_logger-0.1.16.dist-info/METADATA
py_html_logger-0.1.16.dist-info/WHEEL
py_html_logger-0.1.16.dist-info/top_level.txt
py_html_logger-0.1.16.dist-info/RECORD
