Metadata-Version: 2.4
Name: py-html-logger
Version: 0.1.16
Summary: Library for generating HTML logs with support for colors, rotation and filters via JavaScript.
Author-email: Raphael Pires Nome <rphspires@gmail.com>
License-Expression: MIT
Project-URL: Homepage, https://github.com/rphpires/py-html-logger
Project-URL: Bug Tracker, https://github.com/rphpires/py-html-logger/issues
Keywords: logging,html,logger,logs,colors,trace,loghtml,web log,loghtml,py-html-logger,html logger,logging
Classifier: Programming Language :: Python :: 3
Classifier: Operating System :: OS Independent
Classifier: Topic :: System :: Logging
Requires-Python: >=3.8
License-File: LICENSE
Dynamic: license-file
